README.md
setup.py
homoeditdistance/__init__.py
homoeditdistance/__main__.py
homoeditdistance/algorithm.py
homoeditdistance/demonstration.py
homoeditdistance.egg-info/PKG-INFO
homoeditdistance.egg-info/SOURCES.txt
homoeditdistance.egg-info/dependency_links.txt
homoeditdistance.egg-info/entry_points.txt
homoeditdistance.egg-info/requires.txt
homoeditdistance.egg-info/top_level.txt
homoeditdistance/tests/__init__.py
homoeditdistance/tests/test.py