Metadata-Version: 2.1
Name: homoeditdistance
Version: 0.0.1
Summary: An implementation of the homo-edit distance algorithm.
Home-page: https://github.com/AlBi-HHU/homo-edit-distance
Author: Maren Brand, Gunnar W. Klau, Philipp Spohr, Nguyen Khoa Tran, Max Jakub Ried
Author-email: albi-packaging@hhu.de
License: MIT
Platform: UNKNOWN
Classifier: Programming Language :: Python :: 3
Classifier: License :: OSI Approved :: MIT License
Classifier: Operating System :: OS Independent
Classifier: Topic :: Scientific/Engineering :: Bio-Informatics
Requires-Python: >=3.4
